{
  "Version": "2012-10-17",
  "Statement": [
    {
      "Effect": "Allow",
      "Principal": {
        "Federated": "arn:aws:iam::141033868323:oidc-provider/oidc.eks.us-west-1.amazonaws.com/id/47C84E779324FD9D54FB5FC6D20565F4"
      },
      "Action": "sts:AssumeRoleWithWebIdentity",
      "Condition": {
        "StringEquals": {
          "oidc.eks.us-west-1.amazonaws.com/id/47C84E779324FD9D54FB5FC6D20565F4:aud": "sts.amazonaws.com",
          "oidc.eks.us-west-1.amazonaws.com/id/47C84E779324FD9D54FB5FC6D20565F4:sub": "system:serviceaccount:kube-system:ebs-csi-controller-sa"
        }
      }
    }
  ]
}
